pullenti_wrapper/__init__.py
pullenti_wrapper/langs.py
pullenti_wrapper/preprocess.py
pullenti_wrapper/processor.py
pullenti_wrapper/referent.py
pullenti_wrapper/result.py
pullenti_wrapper/utils.py
pullenti_wrapper-0.9.0.dist-info/METADATA
pullenti_wrapper-0.9.0.dist-info/WHEEL
pullenti_wrapper-0.9.0.dist-info/top_level.txt
pullenti_wrapper-0.9.0.dist-info/RECORD
